{
    "table": {
        "icon": "fa fa-info-circle",
        "singlepage": true,
        "id": 1,
        "uuid": 0,
        "tablename": "textos_cart",
        "name": {
            "es": "Textos Carrito",
            "en": ""
        },
        "timestamps": 1,
        "softDeletes": 1,
        "menu_show": 1,
        "slug": 0,
        "slug_global": 0,
        "whoCan": [
            "administrador",
            "developer"
        ]
    },
    "inputs": [
        {
            "isCollapsed": true,
            "columnname": "retirolocal",
            "icon": "",
            "type": "textarea",
            "visible": 1,
            "gridcols": 12,
            "visible_edit": 1,
            "label": {
                "es": "Retiro Local",
                "en": "Retirolocal"
            },
            "unique": 0,
            "default": "",
            "nullable": 1,
            "validate": 1,
            "max": "",
            "min": "",
            "tabledata": "",
            "tablekeycolumn": "",
            "tabletextcolumn": "",
            "translatable": 0,
            "multiple": false
        },
        {
            "isCollapsed": true,
            "columnname": "caba",
            "icon": "",
            "type": "textarea",
            "visible": 1,
            "gridcols": 12,
            "visible_edit": 1,
            "label": {
                "es": "Env\u00edo CABA\/GBA",
                "en": "CABA"
            },
            "unique": 0,
            "default": "",
            "nullable": 1,
            "validate": 1,
            "max": "",
            "min": "",
            "tabledata": "",
            "tablekeycolumn": "",
            "tabletextcolumn": "",
            "translatable": 0,
            "multiple": false
        },
        {
            "isCollapsed": true,
            "columnname": "expreso",
            "icon": "",
            "type": "textarea",
            "visible": 1,
            "gridcols": 12,
            "visible_edit": 1,
            "label": {
                "es": "Expreso",
                "en": "Expreso"
            },
            "unique": 0,
            "default": "",
            "nullable": 1,
            "validate": 1,
            "max": "",
            "min": "",
            "tabledata": "",
            "tablekeycolumn": "",
            "tabletextcolumn": "",
            "translatable": 0,
            "multiple": false
        },
        {
            "isCollapsed": true,
            "columnname": "datos_bancarios",
            "icon": "",
            "type": "textarea",
            "visible": 1,
            "gridcols": 12,
            "visible_edit": 1,
            "label": {
                "es": "Datos Bancarios",
                "en": "Datos_bancarios"
            },
            "unique": 0,
            "default": "",
            "nullable": 1,
            "validate": 1,
            "max": "",
            "min": "",
            "tabledata": "",
            "tablekeycolumn": "",
            "tabletextcolumn": "",
            "translatable": 0,
            "multiple": false
        }
    ],
    "migrate": 0
}